mbbefd.cp39-win_amd64.pyd
mbbefd-0.1.0.dist-info/METADATA
mbbefd-0.1.0.dist-info/WHEEL
mbbefd-0.1.0.dist-info/top_level.txt
mbbefd-0.1.0.dist-info/RECORD
