Metadata-Version: 2.1
Name: mbbefd
Version: 0.1.0
Summary: Univariate and bivariate MBBEFD distributions
License: MIT License
Requires-Python: >=3.9
Requires-Dist: numpy
Requires-Dist: scipy (>=1.9)
Provides-Extra: notebook
Requires-Dist: plotly ; extra == 'notebook'
Requires-Dist: ipykernel ; extra == 'notebook'
Requires-Dist: ipywidgets ; extra == 'notebook'
Requires-Dist: matplotlib ; extra == 'notebook'
Requires-Dist: nbformat (>=4.2) ; extra == 'notebook'
Requires-Dist: numba ; extra == 'notebook'
Requires-Dist: mpmath ; extra == 'notebook'
Requires-Dist: sympy ; extra == 'notebook'
Provides-Extra: test
Requires-Dist: pytest ; extra == 'test'
Requires-Dist: mpmath ; extra == 'test'
